{
    "year": 2019,
    "month": 9,
    "entity": "Verlo",
    "summary": "Database exposed to the internet with no authentication enabled.",
    "tags": {
        "impacted-user-count": 387000,
        "actor": "Hacktivist",
        "initial-access": "Broken Access Control",
        "motive": "Hacktivism:Press"
    },
    "links": [
        "https://threatpost.com/mattress-company-leaks-data-records-of-387k-customers/148530/",
        "https://www.scmagazine.com/home/security-news/data-breach/sleeping-on-the-job-verlo-mattress-factory-exposes-database/"
    ]
}